TiDE/TiDECats.py
TiDE/__init__.py
TiDE/tests/__init__.py
TiDE/utils/__init__.py
TiDE/utils/tide.py
WaveyMcWaveFace/TiDECats.py
WaveyMcWaveFace/__init__.py
WaveyMcWaveFace/tide.py
WaveyMcWaveFace/tests/__init__.py
WaveyMcWaveFace/utils/__init__.py
WaveyMcWaveFace/utils/tide.py
tests/__init__.py
utils/__init__.py
utils/tide.py
WaveyMcWaveFace-1.6.dist-info/METADATA
WaveyMcWaveFace-1.6.dist-info/WHEEL
WaveyMcWaveFace-1.6.dist-info/top_level.txt
WaveyMcWaveFace-1.6.dist-info/RECORD
