Metadata-Version: 2.1
Name: WaveyMcWaveFace
Version: 1.6
Summary: A quick way to run Google's TiDE model
Home-page: https://github.com/AmwayCommon/wavey
Author: Jordan Howell
Author-email: jordan.howell@amway.com
License: MIT
Platform: UNKNOWN
Classifier: License :: OSI Approved :: MIT License
Classifier: Programming Language :: Python :: 3.10
Classifier: Operating System :: OS Independent
Requires-Python: >=3.10
Requires-Dist: numpy
Requires-Dist: pandas
Requires-Dist: pandas-profiling
Requires-Dist: pandocfilters
Requires-Dist: scikit-learn
Requires-Dist: torch
Provides-Extra: dev
Requires-Dist: pytest (==8.2.1) ; extra == 'dev'
Requires-Dist: twine (==5.1.0) ; extra == 'dev'
